monkey_anagram/__init__.py
monkey_anagram/monkey_anagram_solver.py
monkey_anagram/words.txt
monkey_anagram-0.1.dist-info/LICENSE
monkey_anagram-0.1.dist-info/METADATA
monkey_anagram-0.1.dist-info/WHEEL
monkey_anagram-0.1.dist-info/entry_points.txt
monkey_anagram-0.1.dist-info/top_level.txt
monkey_anagram-0.1.dist-info/RECORD
